systemID/__init__.py
systemID/control/__init__.py
systemID/control/controller.py
systemID/core/__init__.py
systemID/core/algorithms/__init__.py
systemID/core/algorithms/controller_eigensystem_realization_algorithm.py
systemID/core/algorithms/eigensystem_realization_algorithm.py
systemID/core/algorithms/eigensystem_realization_algorithm_from_initial_condition_response.py
systemID/core/algorithms/eigensystem_realization_algorithm_with_data_correlation.py
systemID/core/algorithms/eigensystem_realization_algorithm_with_data_correlation_from_initial_condition_response.py
systemID/core/algorithms/markov_controller_parameters_from_observer_controller_markov_parameters.py
systemID/core/algorithms/markov_parameters_from_observer_markov_parameters.py
systemID/core/algorithms/observer_controller_eigensystem_realization_algorithm.py
systemID/core/algorithms/observer_controller_identification_algorithm.py
systemID/core/algorithms/observer_gain_markov_parameters_from_observer_markov_parameters.py
systemID/core/algorithms/observer_kalman_identification_algorithm.py
systemID/core/algorithms/observer_kalman_identification_algorithm_with_observer.py
systemID/core/algorithms/ricatti_equation.py
systemID/core/algorithms/time_varying_controller_markov_parameters_from_time_varying_observer_markov_parameters.py
systemID/core/algorithms/time_varying_controller_observer_gain_markov_parameters_from_time_varying_observer_markov_parameters.py
systemID/core/algorithms/time_varying_eigensystem_realization_algorithm.py
systemID/core/algorithms/time_varying_eigensystem_realization_algorithm_from_initial_condition_response.py
systemID/core/algorithms/time_varying_markov_parameters_from_time_varying_observer_markov_parameters.py
systemID/core/algorithms/time_varying_observer_controller_eigensystem_realization_algorithm.py
systemID/core/algorithms/time_varying_observer_controller_identification_algorithm.py
systemID-25.0.5.dist-info/METADATA
systemID-25.0.5.dist-info/WHEEL
systemID-25.0.5.dist-info/top_level.txt
systemID-25.0.5.dist-info/RECORD
